brickx/__init__.py
brickx/attrs.py
brickx/components.py
brickx/conflicts.py
brickx/elements.py
brickx/node.py
brickx/style.py
brickx/styler.py
brickx-1.1.0.dist-info/LICENSE
brickx-1.1.0.dist-info/METADATA
brickx-1.1.0.dist-info/WHEEL
brickx-1.1.0.dist-info/RECORD
