Metadata-Version: 2.3
Name: brickx
Version: 1.1.0
Summary: Polymorphic builder for styled HTML.
License: MIT
Author: Said Atta
Author-email: saidattaenp@yahoo.fr
Requires-Python: >=3.12
Classifier: License :: OSI Approved :: MIT License
Classifier: Programming Language :: Python :: 3
Classifier: Programming Language :: Python :: 3.12
Classifier: Programming Language :: Python :: 3.13
